stepsel/__init__.py
stepsel/binning/__init__.py
stepsel/binning/helper.py
stepsel/binning/optimal.py
stepsel/data/__init__.py
stepsel/data/dummy_data.parquet
stepsel/data/scoring_table.csv
stepsel/data/scoring_table_invalid.csv
stepsel/data/soccer.parquet
stepsel/datasets.py
stepsel/modeling/__init__.py
stepsel/modeling/predict/__init__.py
stepsel/modeling/predict/scoring_table.py
stepsel/modeling/prep/__init__.py
stepsel/modeling/prep/helper.py
stepsel/modeling/prep/interaction.py
stepsel/modeling/prep/model_matrix.py
stepsel/modeling/stepwise_glm.py
stepsel/stattests/__init__.py
stepsel/stattests/likelihood_ratio_test.py
stepsel/stepsel.py
stepsel/tools/__init__.py
stepsel/tools/group_over_columns.py
stepsel-0.1.0.dist-info/LICENSE
stepsel-0.1.0.dist-info/METADATA
stepsel-0.1.0.dist-info/WHEEL
stepsel-0.1.0.dist-info/RECORD
