Metadata-Version: 2.1
Name: stepsel
Version: 0.1.0
Summary: Stepwise selection for statsmodels GLM.
License: MIT
Author: Jakub Cerny
Requires-Python: >=3.12
Classifier: License :: OSI Approved :: MIT License
Classifier: Programming Language :: Python :: 3
Classifier: Programming Language :: Python :: 3.12
Requires-Dist: matplotlib (>=3.9.2)
Requires-Dist: numpy (>=2.0.0)
Requires-Dist: pandas (>=2.2.2)
Requires-Dist: pyarrow (>=16.1.0)
Requires-Dist: scikit-learn (>=1.5.1)
Requires-Dist: statsmodels (>=0.14.2)
